<annotation>
	<folder>VOC2007</folder>
	<filename>adidas_0_00018.jpg</filename>
	<size>
		<width>600</width>
		<height>450</height>
		<depth>3</depth>
	</size>
	<segmented>0</segmented>
	<object>
		<name>adidas</name>
		<pose>Unspecified</pose>
		<truncated>0</truncated>
		<difficult>0</difficult>
		<bndbox>
			<xmin>148</xmin>
			<ymin>300</ymin>
			<xmax>201</xmax>
			<ymax>338</ymax>
		</bndbox>
	</object>
	<object>
		<name>adidas</name>
		<pose>Unspecified</pose>
		<truncated>0</truncated>
		<difficult>0</difficult>
		<bndbox>
			<xmin>148</xmin>
			<ymin>300</ymin>
			<xmax>201</xmax>
			<ymax>338</ymax>
		</bndbox>
	</object>
	<object>
		<name>adidas</name>
		<pose>Unspecified</pose>
		<truncated>0</truncated>
		<difficult>0</difficult>
		<bndbox>
			<xmin>510</xmin>
			<ymin>3</ymin>
			<xmax>539</xmax>
			<ymax>21</ymax>
		</bndbox>
	</object>
</annotation>
