<annotation>
	<folder>VOC2007</folder>
	<filename>anta_0_00021.jpg</filename>
	<size>
		<width>800</width>
		<height>800</height>
		<depth>3</depth>
	</size>
	<segmented>0</segmented>
	<object>
		<name>anta</name>
		<pose>Unspecified</pose>
		<truncated>0</truncated>
		<difficult>0</difficult>
		<bndbox>
			<xmin>173</xmin>
			<ymin>297</ymin>
			<xmax>256</xmax>
			<ymax>411</ymax>
		</bndbox>
	</object>
	<object>
		<name>anta</name>
		<pose>Unspecified</pose>
		<truncated>0</truncated>
		<difficult>0</difficult>
		<bndbox>
			<xmin>604</xmin>
			<ymin>363</ymin>
			<xmax>723</xmax>
			<ymax>438</ymax>
		</bndbox>
	</object>
</annotation>
