<annotation>
	<folder>VOC2007</folder>
	<filename>erke_0_00156.jpg</filename>
	<size>
		<width>750</width>
		<height>359</height>
		<depth>3</depth>
	</size>
	<segmented>0</segmented>
	<object>
		<name>erke</name>
		<pose>Unspecified</pose>
		<truncated>0</truncated>
		<difficult>0</difficult>
		<bndbox>
			<xmin>29</xmin>
			<ymin>33</ymin>
			<xmax>232</xmax>
			<ymax>99</ymax>
		</bndbox>
	</object>
	<object>
		<name>erke</name>
		<pose>Unspecified</pose>
		<truncated>0</truncated>
		<difficult>0</difficult>
		<bndbox>
			<xmin>416</xmin>
			<ymin>255</ymin>
			<xmax>461</xmax>
			<ymax>277</ymax>
		</bndbox>
	</object>
</annotation>
