<annotation>
	<folder>VOC2007</folder>
	<filename>xtep_0_00178.jpg</filename>
	<size>
		<width>800</width>
		<height>711</height>
		<depth>3</depth>
	</size>
	<segmented>0</segmented>
	<object>
		<name>xtep</name>
		<pose>Unspecified</pose>
		<truncated>0</truncated>
		<difficult>0</difficult>
		<bndbox>
			<xmin>676</xmin>
			<ymin>99</ymin>
			<xmax>780</xmax>
			<ymax>221</ymax>
		</bndbox>
	</object>
	<object>
		<name>xtep</name>
		<pose>Unspecified</pose>
		<truncated>0</truncated>
		<difficult>0</difficult>
		<bndbox>
			<xmin>248</xmin>
			<ymin>373</ymin>
			<xmax>264</xmax>
			<ymax>397</ymax>
		</bndbox>
	</object>
</annotation>
